<?xml version="1.0"?>
<!--<!DOCTYPE metadata SYSTEM "http://www.esri.com/metadata/esriprof80.dtd">-->
<metadata xml:lang="th"><Esri><CreaDate>20121010</CreaDate><CreaTime>15003300</CreaTime><SyncOnce>TRUE</SyncOnce><DataProperties><lineage><Process Name="DefineProjection_1" ToolSource="C:\Program Files\ArcGIS\ArcToolbox\Toolboxes\Data Management Tools.tbx\DefineProjection" Date="20070625" Time="111835">DefineProjection I:\BMAMAP\GISCommon\air_port.shp PROJCS['Indian_1975_UTM_Zone_47N',GEOGCS['GCS_Indian_1975',DATUM['D_Indian_1975',SPHEROID['Everest_Adjustment_1937',6377276.345,300.8017]],PRIMEM['Greenwich',0.0],UNIT['Degree',0.0174532925199433]],PROJECTION['Transverse_Mercator'],PARAMETER['False_Easting',500000.0],PARAMETER['False_Northing',0.0],PARAMETER['Central_Meridian',99.0],PARAMETER['Scale_Factor',0.9996],PARAMETER['Latitude_Of_Origin',0.0],UNIT['Meter',1.0]] I:\BMAMAP\GISCommon\air_port.shp</Process></lineage></DataProperties><MetaID>{4CA66651-8B84-4EDF-B8C2-E8936D1A3AFB}</MetaID></Esri><idinfo><citation><citeinfo><onlink Sync="TRUE"></onlink></citeinfo></citation></idinfo><distInfo><distributor><distorTran><onLineSrc><linkage Sync="TRUE">file://</linkage><protocol Sync="TRUE">Local Area Network</protocol></onLineSrc></distorTran></distributor></distInfo><dataqual><lineage><procstep><procdesc Sync="TRUE">Dataset copied.</procdesc><srcused Sync="TRUE"></srcused><date Sync="TRUE">20070628</date><time Sync="TRUE">09412100</time></procstep><procstep><procdesc Sync="TRUE">Dataset copied.</procdesc><srcused Sync="TRUE"></srcused><date Sync="TRUE">20100512</date><time Sync="TRUE">14063100</time></procstep><procstep><procdesc Sync="TRUE">Dataset copied.</procdesc><srcused Sync="TRUE"></srcused><date Sync="TRUE">20101011</date><time Sync="TRUE">14413300</time></procstep><procstep><procdesc Sync="TRUE">Dataset copied.</procdesc><srcused Sync="TRUE"></srcused><date Sync="TRUE">20120410</date><time Sync="TRUE">09410600</time></procstep><procstep><procdesc Sync="TRUE">Dataset copied.</procdesc><srcused Sync="TRUE"></srcused><date Sync="TRUE">20120829</date><time Sync="TRUE">13564800</time></procstep><procstep><procdesc Sync="TRUE">Dataset copied.</procdesc><srcused Sync="TRUE"></srcused><date Sync="TRUE">20121010</date><time Sync="TRUE">15003300</time></procstep></lineage></dataqual></metadata>
